[
  {
    "email": "jorgeboscan@gmail.com",
    "announcedFlashSale": false,
    "games": [
      {
        "id": "10287",
        "name": "Uncharted 4: A Thief’s End",
        "previousPrice": 59.99,
        "discountedPrice": 0.0,
        "psplusPrice": 0.0,
        "lowestPrice": 59.99,
        "psplusFree": false,
        "discountedFree": false,
        "notifyWhenLowerThan": 0.0,
        "lastUpdateDate": "Jun 4, 2016 2:13:03 PM"
      },
      {
        "id": "10372",
        "name": "The Last Of Us™ Remastered",
        "previousPrice": 49.99,
        "discountedPrice": 0.0,
        "psplusPrice": 0.0,
        "lowestPrice": 49.99,
        "psplusFree": false,
        "discountedFree": false,
        "notifyWhenLowerThan": 0.0,
        "lastUpdateDate": "Jun 4, 2016 2:13:05 PM"
      },
      {
        "id": "81876",
        "name": "Dying Light",
        "previousPrice": 49.99,
        "discountedPrice": 29.99,
        "psplusPrice": 0.0,
        "lowestPrice": 29.99,
        "psplusFree": false,
        "discountedFree": false,
        "notifyWhenLowerThan": 0.0,
        "lastUpdateDate": "Jun 4, 2016 2:13:06 PM"
      },
      {
        "id": "81877",
        "name": "Dying Light Ultimate Edition",
        "previousPrice": 69.99,
        "discountedPrice": 0.0,
        "psplusPrice": 0.0,
        "lowestPrice": 69.99,
        "psplusFree": false,
        "discountedFree": false,
        "notifyWhenLowerThan": 0.0,
        "lastUpdateDate": "Jun 4, 2016 2:13:08 PM"
      },
      {
        "id": "94652",
        "name": "Sniper Elite 3 Ultimate Edition",
        "previousPrice": 39.99,
        "discountedPrice": 0.0,
        "psplusPrice": 0.0,
        "lowestPrice": 39.99,
        "psplusFree": false,
        "discountedFree": false,
        "notifyWhenLowerThan": 0.0,
        "lastUpdateDate": "Jun 4, 2016 2:13:08 PM"
      },
      {
        "id": "96398",
        "name": "DARK SOULS™ II: Scholar of the First Sin",
        "previousPrice": 39.99,
        "discountedPrice": 0.0,
        "psplusPrice": 0.0,
        "lowestPrice": 39.99,
        "psplusFree": false,
        "discountedFree": false,
        "notifyWhenLowerThan": 0.0,
        "lastUpdateDate": "Jun 4, 2016 2:13:10 PM"
      },
      {
        "id": "98432",
        "name": "Project CARS",
        "previousPrice": 39.99,
        "discountedPrice": 29.99,
        "psplusPrice": 0.0,
        "lowestPrice": 29.99,
        "psplusFree": false,
        "discountedFree": false,
        "notifyWhenLowerThan": 0.0,
        "lastUpdateDate": "Jun 4, 2016 2:13:11 PM"
      },
      {
        "id": "100526",
        "name": "Ratchet \u0026 Clank™",
        "previousPrice": 39.99,
        "discountedPrice": 0.0,
        "psplusPrice": 0.0,
        "lowestPrice": 39.99,
        "psplusFree": false,
        "discountedFree": false,
        "notifyWhenLowerThan": 0.0,
        "lastUpdateDate": "Jun 4, 2016 2:13:12 PM"
      },
      {
        "id": "103417",
        "name": "Mad Max",
        "previousPrice": 49.99,
        "discountedPrice": 39.99,
        "psplusPrice": 0.0,
        "lowestPrice": 39.99,
        "psplusFree": false,
        "discountedFree": false,
        "notifyWhenLowerThan": 0.0,
        "lastUpdateDate": "Jun 4, 2016 2:13:13 PM"
      },
      {
        "id": "126529",
        "name": "Mortal Kombat XL",
        "previousPrice": 59.99,
        "discountedPrice": 0.0,
        "psplusPrice": 0.0,
        "lowestPrice": 59.99,
        "psplusFree": false,
        "discountedFree": false,
        "notifyWhenLowerThan": 0.0,
        "lastUpdateDate": "Jun 4, 2016 2:13:14 PM"
      },
      {
        "id": "126538",
        "name": "Dying Light: The Following - Enhanced Edition",
        "previousPrice": 59.99,
        "discountedPrice": 0.0,
        "psplusPrice": 0.0,
        "lowestPrice": 59.99,
        "psplusFree": false,
        "discountedFree": false,
        "notifyWhenLowerThan": 0.0,
        "lastUpdateDate": "Jun 4, 2016 2:13:15 PM"
      },
      {
        "id": "147833",
        "name": "DARK SOULS™ III",
        "previousPrice": 59.99,
        "discountedPrice": 0.0,
        "psplusPrice": 0.0,
        "lowestPrice": 59.99,
        "psplusFree": false,
        "discountedFree": false,
        "notifyWhenLowerThan": 0.0,
        "lastUpdateDate": "Jun 4, 2016 2:13:16 PM"
      },
      {
        "id": "191256",
        "name": "No Man\u0027s Sky",
        "previousPrice": 59.99,
        "discountedPrice": 0.0,
        "psplusPrice": 0.0,
        "lowestPrice": 59.99,
        "psplusFree": false,
        "discountedFree": false,
        "notifyWhenLowerThan": 0.0,
        "lastUpdateDate": "Jun 4, 2016 2:13:17 PM"
      },
      {
        "id": "191545",
        "name": "Salt and Sanctuary",
        "previousPrice": 17.99,
        "discountedPrice": 0.0,
        "psplusPrice": 0.0,
        "lowestPrice": 17.99,
        "psplusFree": false,
        "discountedFree": false,
        "notifyWhenLowerThan": 0.0,
        "lastUpdateDate": "Jun 4, 2016 2:13:18 PM"
      }
    ]
  }
]